twomartens.allrisscraper-0.5.9-py3.8-nspkg.pth
twomartens/allrisscraper/__init__.py
twomartens/allrisscraper/__main__.py
twomartens/allrisscraper/agenda.py
twomartens/allrisscraper/config.py
twomartens/allrisscraper/custom_json.py
twomartens/allrisscraper/data_types.py
twomartens/allrisscraper/definitions.py
twomartens/allrisscraper/internal.py
twomartens/allrisscraper/main.py
twomartens/allrisscraper/meeting.py
twomartens/allrisscraper/organization.py
twomartens/allrisscraper/person.py
twomartens/allrisscraper/public.py
twomartens.allrisscraper-0.5.9.dist-info/LICENSE
twomartens.allrisscraper-0.5.9.dist-info/METADATA
twomartens.allrisscraper-0.5.9.dist-info/WHEEL
twomartens.allrisscraper-0.5.9.dist-info/entry_points.txt
twomartens.allrisscraper-0.5.9.dist-info/namespace_packages.txt
twomartens.allrisscraper-0.5.9.dist-info/top_level.txt
twomartens.allrisscraper-0.5.9.dist-info/RECORD
