Metadata-Version: 2.1
Name: twomartens.allrisscraper
Version: 0.5.9
Summary: Scraper for ALLRIS
Home-page: https://git.2martens.de/2martens/allris-scraper
Author: Jim Martens
Author-email: github@2martens.de
License: Apache License 2.0
Platform: UNKNOWN
Classifier: Operating System :: OS Independent
Classifier: Development Status :: 3 - Alpha
Classifier: License :: OSI Approved :: Apache Software License
Classifier: Environment :: Console
Classifier: Topic :: Utilities
Classifier: Programming Language :: Python
Classifier: Programming Language :: Python :: 3
Classifier: Programming Language :: Python :: 3.7
Classifier: Programming Language :: Python :: 3.8
Requires-Python: ~=3.7
License-File: LICENSE
Requires-Dist: selenium
